emrichen/__init__.py
emrichen/__main__.py
emrichen/cli.py
emrichen/context.py
emrichen/documents_list.py
emrichen/exceptions.py
emrichen/output.py
emrichen/template.py
emrichen/void.py
emrichen/input/__init__.py
emrichen/input/json.py
emrichen/input/utils.py
emrichen/input/yaml.py
emrichen/tags/__init__.py
emrichen/tags/all.py
emrichen/tags/any.py
emrichen/tags/base.py
emrichen/tags/base64.py
emrichen/tags/compose.py
emrichen/tags/concat.py
emrichen/tags/debug.py
emrichen/tags/defaults.py
emrichen/tags/error.py
emrichen/tags/exists.py
emrichen/tags/filter.py
emrichen/tags/format.py
emrichen/tags/hash.py
emrichen/tags/if_.py
emrichen/tags/include.py
emrichen/tags/index.py
emrichen/tags/join.py
emrichen/tags/lookup.py
emrichen/tags/loop.py
emrichen/tags/merge.py
emrichen/tags/not_.py
emrichen/tags/op.py
emrichen/tags/typeop.py
emrichen/tags/urlencode.py
emrichen/tags/var.py
emrichen/tags/void.py
emrichen/tags/with_.py
emrichen-0.4.0.dist-info/LICENSE
emrichen-0.4.0.dist-info/METADATA
emrichen-0.4.0.dist-info/WHEEL
emrichen-0.4.0.dist-info/entry_points.txt
emrichen-0.4.0.dist-info/top_level.txt
emrichen-0.4.0.dist-info/zip-safe
emrichen-0.4.0.dist-info/RECORD
