Metadata-Version: 2.1
Name: emrichen
Version: 0.4.0
Summary: Template engine for YAML & JSON
Home-page: http://github.com/con2/emrichen
Author: Santtu Pajukanta
Author-email: santtu@pajukanta.fi
License: MIT
Requires-Python: >=3.6
Provides-Extra: test
Provides-Extra: lint
License-File: LICENSE
